{
    "type": "Feature",
    "id": 2494497,
    "properties": {
        "woe_id": 2494497,
        "place_id": "62jvJmibBZVq8ywR",
        "place_type": "locality",
        "place_type_id": 7,
        "label": "Slab City, New York, United States"
    },
    "geometry": {
        "type": "MultiPolygon",
        "created": 1292422443,
        "alpha": 0.00015,
        "points": 5,
        "edges": 6,
        "is_donuthole": 0,
        "link": {
            "href": "http:\/\/farm6.static.flickr.com\/5202\/shapefiles\/2494497_20101215_53ec0ce94c.tar.gz"
        },
        "bbox": [
            -75.148246765137,
            44.653224945068,
            -75.129379272461,
            44.663120269775
        ],
        "coordinates": [
            [
                [
                    [
                        -75.136856,
                        44.653225
                    ],
                    [
                        -75.148247,
                        44.653831
                    ],
                    [
                        -75.132179,
                        44.66312
                    ],
                    [
                        -75.131638,
                        44.662739
                    ],
                    [
                        -75.129379,
                        44.660515
                    ],
                    [
                        -75.136856,
                        44.653225
                    ]
                ]
            ]
        ]
    }
}