{
    "type": "Feature",
    "id": 2375896,
    "properties": {
        "woe_id": 2375896,
        "place_id": "Lbwdo46bApthlhtz",
        "place_type": "locality",
        "place_type_id": 7,
        "label": "Cascade Gorge, Oregon, United States"
    },
    "geometry": {
        "type": "MultiPolygon",
        "created": 1292545647,
        "alpha": 0.00015,
        "points": 17,
        "edges": 11,
        "is_donuthole": 0,
        "link": {
            "href": "http:\/\/farm6.static.flickr.com\/5165\/shapefiles\/2375896_20101217_48d998de63.tar.gz"
        },
        "bbox": [
            -122.59149932861,
            42.704418182373,
            -122.55746459961,
            42.722045898438
        ],
        "coordinates": [
            [
                [
                    [
                        -122.568542,
                        42.714607
                    ],
                    [
                        -122.569466,
                        42.714699
                    ],
                    [
                        -122.579498,
                        42.712715
                    ],
                    [
                        -122.591499,
                        42.704418
                    ],
                    [
                        -122.590942,
                        42.713722
                    ],
                    [
                        -122.579498,
                        42.712715
                    ],
                    [
                        -122.570343,
                        42.717381
                    ],
                    [
                        -122.561417,
                        42.722046
                    ],
                    [
                        -122.557465,
                        42.720596
                    ],
                    [
                        -122.56472,
                        42.71711
                    ],
                    [
                        -122.568542,
                        42.714607
                    ]
                ]
            ]
        ]
    }
}