{
    "type": "Feature",
    "id": 2454998,
    "properties": {
        "woe_id": 2454998,
        "place_id": "KDhHtjibBZlE2CvQ",
        "place_type": "locality",
        "place_type_id": 7,
        "label": "Mount Holly, Vermont, United States"
    },
    "geometry": {
        "type": "MultiPolygon",
        "created": 1292550245,
        "alpha": 0.00015,
        "points": 14,
        "edges": 7,
        "is_donuthole": 0,
        "link": {
            "href": "http:\/\/farm6.static.flickr.com\/5047\/shapefiles\/2454998_20101217_e59bbe84be.tar.gz"
        },
        "bbox": [
            -72.824462890625,
            43.438705444336,
            -72.806137084961,
            43.454536437988
        ],
        "coordinates": [
            [
                [
                    [
                        -72.824463,
                        43.448994
                    ],
                    [
                        -72.824226,
                        43.45245
                    ],
                    [
                        -72.819916,
                        43.454536
                    ],
                    [
                        -72.806137,
                        43.453526
                    ],
                    [
                        -72.814804,
                        43.448994
                    ],
                    [
                        -72.822487,
                        43.438705
                    ],
                    [
                        -72.824463,
                        43.448994
                    ]
                ]
            ]
        ]
    }
}