{
    "type": "Feature",
    "id": 349922,
    "properties": {
        "woe_id": 349922,
        "place_id": "7ZkyU7aaBZWuMwU",
        "place_type": "locality",
        "place_type_id": 7,
        "label": "Loncoche, Araucania Region, Chile"
    },
    "geometry": {
        "type": "MultiPolygon",
        "created": 1292523894,
        "alpha": 0.00015,
        "points": 14,
        "edges": 9,
        "is_donuthole": 0,
        "link": {
            "href": "http:\/\/farm6.static.flickr.com\/5242\/shapefiles\/349922_20101216_dba8855fa9.tar.gz"
        },
        "bbox": [
            -72.635932922363,
            -39.372524261475,
            -72.62134552002,
            -39.363964080811
        ],
        "coordinates": [
            [
                [
                    [
                        -72.623749,
                        -39.368279
                    ],
                    [
                        -72.627869,
                        -39.372524
                    ],
                    [
                        -72.635933,
                        -39.368477
                    ],
                    [
                        -72.63456,
                        -39.367882
                    ],
                    [
                        -72.633362,
                        -39.367481
                    ],
                    [
                        -72.627182,
                        -39.364033
                    ],
                    [
                        -72.625633,
                        -39.363964
                    ],
                    [
                        -72.621346,
                        -39.364563
                    ],
                    [
                        -72.623749,
                        -39.368279
                    ]
                ]
            ]
        ]
    }
}