{
    "type": "Feature",
    "id": 506349,
    "properties": {
        "woe_id": 506349,
        "place_id": "kWn08G6cAZpe1AY",
        "place_type": "locality",
        "place_type_id": 7,
        "label": "Ma\u0142e Swornegacie, Pomeranian, Poland"
    },
    "geometry": {
        "type": "MultiPolygon",
        "created": 1292453450,
        "alpha": 0.00015,
        "points": 11,
        "edges": 7,
        "is_donuthole": 0,
        "link": {
            "href": "http:\/\/farm6.static.flickr.com\/5122\/shapefiles\/506349_20101215_7e355b5d8d.tar.gz"
        },
        "bbox": [
            17.532218933105,
            53.815044403076,
            17.560194015503,
            53.826835632324
        ],
        "coordinates": [
            [
                [
                    [
                        17.53228,
                        53.817364
                    ],
                    [
                        17.532219,
                        53.817581
                    ],
                    [
                        17.548643,
                        53.826836
                    ],
                    [
                        17.560194,
                        53.815044
                    ],
                    [
                        17.544979,
                        53.818001
                    ],
                    [
                        17.532463,
                        53.816864
                    ],
                    [
                        17.53228,
                        53.817364
                    ]
                ]
            ]
        ]
    }
}