{
    "type": "Feature",
    "id": 28570131,
    "properties": {
        "woe_id": 28570131,
        "place_id": "q4vEo2qbCZlGCXqKrA",
        "place_type": "neighbourhood",
        "place_type_id": 22,
        "label": "Horyujikita 1 Chome, Ikaruga-cho, Nara Prefecture, JP, Japan"
    },
    "geometry": {
        "type": "MultiPolygon",
        "created": 1292527262,
        "alpha": 1.0e-5,
        "points": 41,
        "edges": 19,
        "is_donuthole": 0,
        "link": {
            "href": "http:\/\/farm6.static.flickr.com\/5041\/shapefiles\/28570131_20101216_5edf6df988.tar.gz"
        },
        "bbox": [
            135.72973632812,
            34.614334106445,
            135.73933410645,
            34.622001647949
        ],
        "coordinates": [
            [
                [
                    [
                        135.734726,
                        34.614464
                    ],
                    [
                        135.734695,
                        34.614471
                    ],
                    [
                        135.734512,
                        34.614513
                    ],
                    [
                        135.734192,
                        34.614655
                    ],
                    [
                        135.734116,
                        34.61478
                    ],
                    [
                        135.733597,
                        34.615692
                    ],
                    [
                        135.731613,
                        34.617031
                    ],
                    [
                        135.730423,
                        34.619576
                    ],
                    [
                        135.729736,
                        34.620777
                    ],
                    [
                        135.734116,
                        34.620213
                    ],
                    [
                        135.737717,
                        34.621696
                    ],
                    [
                        135.739166,
                        34.622002
                    ],
                    [
                        135.739334,
                        34.622002
                    ],
                    [
                        135.738144,
                        34.618797
                    ],
                    [
                        135.739212,
                        34.614807
                    ],
                    [
                        135.738708,
                        34.614803
                    ],
                    [
                        135.735825,
                        34.614437
                    ],
                    [
                        135.735336,
                        34.614334
                    ],
                    [
                        135.734726,
                        34.614464
                    ]
                ]
            ]
        ]
    }
}