{
    "type": "Feature",
    "id": 723689,
    "properties": {
        "woe_id": 723689,
        "place_id": "x5HEJhKeA58osXc",
        "place_type": "locality",
        "place_type_id": 7,
        "label": "Santo Stefano di Camastra, Sicily, Italy"
    },
    "geometry": {
        "type": "MultiPolygon",
        "created": 1292530535,
        "alpha": 0.00015,
        "points": 52,
        "edges": 10,
        "is_donuthole": 0,
        "link": {
            "href": "http:\/\/farm6.static.flickr.com\/5286\/shapefiles\/723689_20101216_0fe3f2f120.tar.gz"
        },
        "bbox": [
            14.332951545715,
            38.006443023682,
            14.358336448669,
            38.018207550049
        ],
        "coordinates": [
            [
                [
                    [
                        14.350118,
                        38.018208
                    ],
                    [
                        14.354152,
                        38.017872
                    ],
                    [
                        14.358336,
                        38.014057
                    ],
                    [
                        14.355697,
                        38.007793
                    ],
                    [
                        14.346084,
                        38.006443
                    ],
                    [
                        14.339904,
                        38.006443
                    ],
                    [
                        14.332952,
                        38.016586
                    ],
                    [
                        14.346342,
                        38.017872
                    ],
                    [
                        14.350097,
                        38.018208
                    ],
                    [
                        14.350118,
                        38.018208
                    ]
                ]
            ]
        ]
    }
}