{
    "type": "Feature",
    "id": 2497131,
    "properties": {
        "woe_id": 2497131,
        "place_id": "ihL3TBmbBZX5QPUh",
        "place_type": "neighbourhood",
        "place_type_id": 22,
        "label": "Southridge, Birmingham, AL, US, United States"
    },
    "geometry": {
        "type": "MultiPolygon",
        "created": 1292530921,
        "alpha": 1.0e-5,
        "points": 11,
        "edges": 10,
        "is_donuthole": 0,
        "link": {
            "href": "http:\/\/farm6.static.flickr.com\/5288\/shapefiles\/2497131_20101216_923c65ee9a.tar.gz"
        },
        "bbox": [
            -86.793022155762,
            33.434734344482,
            -86.78369140625,
            33.444080352783
        ],
        "coordinates": [
            [
                [
                    [
                        -86.787399,
                        33.435577
                    ],
                    [
                        -86.789246,
                        33.434734
                    ],
                    [
                        -86.790573,
                        33.436241
                    ],
                    [
                        -86.790253,
                        33.440071
                    ],
                    [
                        -86.793022,
                        33.442627
                    ],
                    [
                        -86.79113,
                        33.44408
                    ],
                    [
                        -86.78933,
                        33.44231
                    ],
                    [
                        -86.785423,
                        33.439819
                    ],
                    [
                        -86.783691,
                        33.439068
                    ],
                    [
                        -86.787399,
                        33.435577
                    ]
                ]
            ]
        ]
    }
}