{
    "type": "Feature",
    "id": 752149,
    "properties": {
        "woe_id": 752149,
        "place_id": "jP5bMPmeBJ4ajc8",
        "place_type": "locality",
        "place_type_id": 7,
        "label": "Almacelles, Catalonia, Spain"
    },
    "geometry": {
        "type": "MultiPolygon",
        "created": 1292521865,
        "alpha": 0.00015,
        "points": 8,
        "edges": 6,
        "is_donuthole": 0,
        "link": {
            "href": "http:\/\/farm6.static.flickr.com\/5208\/shapefiles\/752149_20101216_89a1c08b96.tar.gz"
        },
        "bbox": [
            0.43610501289368,
            41.731155395508,
            0.44322898983955,
            41.739040374756
        ],
        "coordinates": [
            [
                [
                    [
                        0.436706,
                        41.737503
                    ],
                    [
                        0.443229,
                        41.73904
                    ],
                    [
                        0.438208,
                        41.731155
                    ],
                    [
                        0.43726,
                        41.731258
                    ],
                    [
                        0.436105,
                        41.73214
                    ],
                    [
                        0.436706,
                        41.737503
                    ]
                ]
            ]
        ]
    }
}