{
    "type": "Feature",
    "id": 1443405,
    "properties": {
        "woe_id": 1443405,
        "place_id": "V0HVIaGYBZjy7wBY",
        "place_type": "locality",
        "place_type_id": 7,
        "label": "Dabaga, Iringa, Tanzania"
    },
    "geometry": {
        "type": "MultiPolygon",
        "created": 1292547361,
        "alpha": 0.00015,
        "points": 16,
        "edges": 7,
        "is_donuthole": 0,
        "link": {
            "href": "http:\/\/farm6.static.flickr.com\/5042\/shapefiles\/1443405_20101217_d0acb24fc9.tar.gz"
        },
        "bbox": [
            35.954261779785,
            -8.1126365661621,
            35.962284088135,
            -8.1055421829224
        ],
        "coordinates": [
            [
                [
                    [
                        35.958336,
                        -8.111618
                    ],
                    [
                        35.954262,
                        -8.111195
                    ],
                    [
                        35.958164,
                        -8.107072
                    ],
                    [
                        35.96207,
                        -8.105542
                    ],
                    [
                        35.962284,
                        -8.109026
                    ],
                    [
                        35.961514,
                        -8.112637
                    ],
                    [
                        35.958336,
                        -8.111618
                    ]
                ]
            ]
        ]
    }
}