{
    "type": "Feature",
    "id": 28533238,
    "properties": {
        "woe_id": 28533238,
        "place_id": "9kliYdObCZmVjKwdWQ",
        "place_type": "neighbourhood",
        "place_type_id": 22,
        "label": "Shimoshinjo 1 Chome, Kawasaki-shi, Kanagawa Prefecture, JP, Japan"
    },
    "geometry": {
        "type": "MultiPolygon",
        "created": 1292519170,
        "alpha": 1.0e-5,
        "points": 7,
        "edges": 7,
        "is_donuthole": 0,
        "link": {
            "href": "http:\/\/farm6.static.flickr.com\/5126\/shapefiles\/28533238_20101216_10a33fd356.tar.gz"
        },
        "bbox": [
            139.63549804688,
            35.579334259033,
            139.63575744629,
            35.580711364746
        ],
        "coordinates": [
            [
                [
                    [
                        139.635727,
                        35.580711
                    ],
                    [
                        139.635742,
                        35.580708
                    ],
                    [
                        139.635757,
                        35.580704
                    ],
                    [
                        139.635757,
                        35.580544
                    ],
                    [
                        139.635498,
                        35.579334
                    ],
                    [
                        139.635681,
                        35.580654
                    ],
                    [
                        139.635727,
                        35.580711
                    ]
                ]
            ]
        ]
    }
}