{
    "type": "Feature",
    "id": 28533222,
    "properties": {
        "woe_id": 28533222,
        "place_id": "MVoqiXebCZl8.N.75Q",
        "place_type": "neighbourhood",
        "place_type_id": 22,
        "label": "Kamimarukosannocho 1 Chome, Kawasaki-shi, Kanagawa Prefecture, JP, Japan"
    },
    "geometry": {
        "type": "MultiPolygon",
        "created": 1292524365,
        "alpha": 1.0e-5,
        "points": 64,
        "edges": 14,
        "is_donuthole": 0,
        "link": {
            "href": "http:\/\/farm6.static.flickr.com\/5206\/shapefiles\/28533222_20101216_181c6d8b23.tar.gz"
        },
        "bbox": [
            139.66716003418,
            35.578643798828,
            139.67149353027,
            35.583103179932
        ],
        "coordinates": [
            [
                [
                    [
                        139.670914,
                        35.582436
                    ],
                    [
                        139.671494,
                        35.581139
                    ],
                    [
                        139.671204,
                        35.578644
                    ],
                    [
                        139.669159,
                        35.5788
                    ],
                    [
                        139.667801,
                        35.5788
                    ],
                    [
                        139.66716,
                        35.579605
                    ],
                    [
                        139.668121,
                        35.580051
                    ],
                    [
                        139.668488,
                        35.580338
                    ],
                    [
                        139.670273,
                        35.582336
                    ],
                    [
                        139.6707,
                        35.583061
                    ],
                    [
                        139.670731,
                        35.583103
                    ],
                    [
                        139.670837,
                        35.583092
                    ],
                    [
                        139.670868,
                        35.582695
                    ],
                    [
                        139.670914,
                        35.582436
                    ]
                ]
            ]
        ]
    }
}