{
    "type": "Feature",
    "id": 2484239,
    "properties": {
        "woe_id": 2484239,
        "place_id": "64di8DebBZRaoa9y",
        "place_type": "locality",
        "place_type_id": 7,
        "label": "Rome, Illinois, United States"
    },
    "geometry": {
        "type": "MultiPolygon",
        "created": 1292448901,
        "alpha": 0.000457763671875,
        "points": 31,
        "edges": 14,
        "is_donuthole": 0,
        "link": {
            "href": "http:\/\/farm6.static.flickr.com\/5210\/shapefiles\/2484239_20101215_e8018d1e7f.tar.gz"
        },
        "bbox": [
            -89.560333251953,
            40.875587463379,
            -89.437789916992,
            40.89669418335
        ],
        "coordinates": [
            [
                [
                    [
                        -89.453346,
                        40.87989
                    ],
                    [
                        -89.43779,
                        40.875587
                    ],
                    [
                        -89.453644,
                        40.878574
                    ],
                    [
                        -89.460236,
                        40.87941
                    ],
                    [
                        -89.498726,
                        40.877689
                    ],
                    [
                        -89.527161,
                        40.878868
                    ],
                    [
                        -89.560333,
                        40.886833
                    ],
                    [
                        -89.526237,
                        40.881432
                    ],
                    [
                        -89.513031,
                        40.892971
                    ],
                    [
                        -89.504929,
                        40.896694
                    ],
                    [
                        -89.498466,
                        40.893131
                    ],
                    [
                        -89.495483,
                        40.891567
                    ],
                    [
                        -89.457764,
                        40.882629
                    ],
                    [
                        -89.453346,
                        40.87989
                    ]
                ]
            ]
        ]
    }
}