{
    "type": "Feature",
    "id": 2211082,
    "properties": {
        "woe_id": 2211082,
        "place_id": "h3RWFI.bA52OFKVw",
        "place_type": "locality",
        "place_type_id": 7,
        "label": "Kalar Kahar, Punjab, Pakistan"
    },
    "geometry": {
        "type": "MultiPolygon",
        "created": 1292525346,
        "alpha": 0.00015,
        "points": 15,
        "edges": 13,
        "is_donuthole": 0,
        "link": {
            "href": "http:\/\/farm6.static.flickr.com\/5249\/shapefiles\/2211082_20101216_ab0d28a9a3.tar.gz"
        },
        "bbox": [
            72.690864562988,
            32.757827758789,
            72.725372314453,
            32.793834686279
        ],
        "coordinates": [
            [
                [
                    [
                        72.706833,
                        32.77544
                    ],
                    [
                        72.70752,
                        32.775078
                    ],
                    [
                        72.714729,
                        32.771397
                    ],
                    [
                        72.716942,
                        32.769444
                    ],
                    [
                        72.7173,
                        32.769089
                    ],
                    [
                        72.725372,
                        32.757828
                    ],
                    [
                        72.703224,
                        32.762089
                    ],
                    [
                        72.699997,
                        32.759998
                    ],
                    [
                        72.690887,
                        32.778851
                    ],
                    [
                        72.690865,
                        32.783161
                    ],
                    [
                        72.695,
                        32.793835
                    ],
                    [
                        72.699448,
                        32.779625
                    ],
                    [
                        72.706833,
                        32.77544
                    ]
                ]
            ]
        ]
    }
}