{
    "type": "Feature",
    "id": 20111274,
    "properties": {
        "woe_id": 20111274,
        "place_id": "kOL3FdebAZ2ItdmiqQ",
        "place_type": "locality",
        "place_type_id": 7,
        "label": "Belverde, Tuscany, Italy"
    },
    "geometry": {
        "type": "MultiPolygon",
        "created": 1292451925,
        "alpha": 0.00015,
        "points": 21,
        "edges": 9,
        "is_donuthole": 0,
        "link": {
            "href": "http:\/\/farm6.static.flickr.com\/5008\/shapefiles\/20111274_20101215_f7e28418be.tar.gz"
        },
        "bbox": [
            11.297377586365,
            43.333587646484,
            11.316088676453,
            43.347152709961
        ],
        "coordinates": [
            [
                [
                    [
                        11.308933,
                        43.334625
                    ],
                    [
                        11.302356,
                        43.338539
                    ],
                    [
                        11.297378,
                        43.347153
                    ],
                    [
                        11.309652,
                        43.345779
                    ],
                    [
                        11.314544,
                        43.344154
                    ],
                    [
                        11.315059,
                        43.344032
                    ],
                    [
                        11.316089,
                        43.343655
                    ],
                    [
                        11.310401,
                        43.333588
                    ],
                    [
                        11.308933,
                        43.334625
                    ]
                ]
            ]
        ]
    }
}