{
    "type": "Feature",
    "id": 55971130,
    "properties": {
        "woe_id": 55971130,
        "place_id": "mfe8Q0mcBJWLX6Pmug",
        "place_type": "neighbourhood",
        "place_type_id": 22,
        "label": "Evans, San Jose, CA, US, United States"
    },
    "geometry": {
        "type": "MultiPolygon",
        "created": 1292520465,
        "alpha": 1.0e-5,
        "points": 9,
        "edges": 9,
        "is_donuthole": 0,
        "link": {
            "href": "http:\/\/farm6.static.flickr.com\/5008\/shapefiles\/55971130_20101216_8b7187ab85.tar.gz"
        },
        "bbox": [
            -121.874168396,
            37.293998718262,
            -121.87117767334,
            37.29655456543
        ],
        "coordinates": [
            [
                [
                    [
                        -121.873337,
                        37.296165
                    ],
                    [
                        -121.872635,
                        37.296555
                    ],
                    [
                        -121.872498,
                        37.296497
                    ],
                    [
                        -121.871178,
                        37.295494
                    ],
                    [
                        -121.872337,
                        37.294666
                    ],
                    [
                        -121.872772,
                        37.29425
                    ],
                    [
                        -121.874001,
                        37.293999
                    ],
                    [
                        -121.874168,
                        37.295502
                    ],
                    [
                        -121.873337,
                        37.296165
                    ]
                ]
            ]
        ]
    }
}