{
    "type": "Feature",
    "id": 29390586,
    "properties": {
        "woe_id": 29390586,
        "place_id": "VCDLTC2bCJ8furBVaA",
        "place_type": "county",
        "place_type_id": 9,
        "label": "Merkez, Rize, Turkey"
    },
    "geometry": {
        "type": "MultiPolygon",
        "created": 1292536161,
        "alpha": 0.0015,
        "points": 50,
        "edges": 9,
        "is_donuthole": 0,
        "link": {
            "href": "http:\/\/farm6.static.flickr.com\/5047\/shapefiles\/29390586_20101216_08e6a55503.tar.gz"
        },
        "bbox": [
            40.482215881348,
            40.989875793457,
            40.605556488037,
            41.071067810059
        ],
        "coordinates": [
            [
                [
                    [
                        40.515518,
                        41.01313
                    ],
                    [
                        40.482216,
                        41.024204
                    ],
                    [
                        40.490112,
                        41.056572
                    ],
                    [
                        40.517578,
                        41.071068
                    ],
                    [
                        40.5653,
                        41.038059
                    ],
                    [
                        40.605556,
                        41.048889
                    ],
                    [
                        40.561523,
                        41.004776
                    ],
                    [
                        40.540924,
                        40.989876
                    ],
                    [
                        40.515518,
                        41.01313
                    ]
                ]
            ]
        ]
    }
}