{
    "type": "Feature",
    "id": 2493066,
    "properties": {
        "woe_id": 2493066,
        "place_id": "yRUC5zibBZVzd5SV",
        "place_type": "neighbourhood",
        "place_type_id": 22,
        "label": "Shore Acres, Rochester, NY, US, United States"
    },
    "geometry": {
        "type": "MultiPolygon",
        "created": 1292449928,
        "alpha": 1.0e-5,
        "points": 25,
        "edges": 12,
        "is_donuthole": 0,
        "link": {
            "href": "http:\/\/farm6.static.flickr.com\/5087\/shapefiles\/2493066_20101215_e1e7c695a9.tar.gz"
        },
        "bbox": [
            -77.634254455566,
            43.262977600098,
            -77.626129150391,
            43.270080566406
        ],
        "coordinates": [
            [
                [
                    [
                        -77.634201,
                        43.264587
                    ],
                    [
                        -77.632484,
                        43.269707
                    ],
                    [
                        -77.630684,
                        43.269081
                    ],
                    [
                        -77.627937,
                        43.269768
                    ],
                    [
                        -77.626991,
                        43.270081
                    ],
                    [
                        -77.626221,
                        43.269527
                    ],
                    [
                        -77.626129,
                        43.269405
                    ],
                    [
                        -77.627052,
                        43.268917
                    ],
                    [
                        -77.630341,
                        43.268208
                    ],
                    [
                        -77.632004,
                        43.262978
                    ],
                    [
                        -77.634254,
                        43.264427
                    ],
                    [
                        -77.634201,
                        43.264587
                    ]
                ]
            ]
        ]
    }
}