{
    "type": "Feature",
    "id": 28645393,
    "properties": {
        "woe_id": 28645393,
        "place_id": "dvvidvibCZquvwquEw",
        "place_type": "locality",
        "place_type_id": 7,
        "label": "Tabourie Lake, New South Wales, Australia"
    },
    "geometry": {
        "type": "MultiPolygon",
        "created": 1292531099,
        "alpha": 0.00015,
        "points": 16,
        "edges": 11,
        "is_donuthole": 0,
        "link": {
            "href": "http:\/\/farm6.static.flickr.com\/5205\/shapefiles\/28645393_20101216_8ece3b1742.tar.gz"
        },
        "bbox": [
            150.41003417969,
            -35.445323944092,
            150.42753601074,
            -35.40710067749
        ],
        "coordinates": [
            [
                [
                    [
                        150.413818,
                        -35.445324
                    ],
                    [
                        150.411591,
                        -35.436966
                    ],
                    [
                        150.410934,
                        -35.431515
                    ],
                    [
                        150.410034,
                        -35.427383
                    ],
                    [
                        150.414841,
                        -35.421791
                    ],
                    [
                        150.420776,
                        -35.407101
                    ],
                    [
                        150.427536,
                        -35.416553
                    ],
                    [
                        150.425339,
                        -35.418247
                    ],
                    [
                        150.414841,
                        -35.431442
                    ],
                    [
                        150.41452,
                        -35.443642
                    ],
                    [
                        150.413818,
                        -35.445324
                    ]
                ]
            ]
        ]
    }
}