{
    "type": "Feature",
    "id": 28536901,
    "properties": {
        "woe_id": 28536901,
        "place_id": "heH2_OCbCZkRxIQSmg",
        "place_type": "neighbourhood",
        "place_type_id": 22,
        "label": "Tsumarichohigashi 2 Chome, Tokamachi-shi, Niigata Prefecture, JP, Japan"
    },
    "geometry": {
        "type": "MultiPolygon",
        "created": 1292472371,
        "alpha": 1.0e-5,
        "points": 7,
        "edges": 5,
        "is_donuthole": 0,
        "link": {
            "href": "http:\/\/farm6.static.flickr.com\/5287\/shapefiles\/28536901_20101216_53fc465a91.tar.gz"
        },
        "bbox": [
            138.7508392334,
            37.113967895508,
            138.75166320801,
            37.118167877197
        ],
        "coordinates": [
            [
                [
                    [
                        138.750931,
                        37.113968
                    ],
                    [
                        138.750839,
                        37.113998
                    ],
                    [
                        138.751007,
                        37.118168
                    ],
                    [
                        138.751663,
                        37.114166
                    ],
                    [
                        138.750931,
                        37.113968
                    ]
                ]
            ]
        ]
    }
}