{
    "type": "Feature",
    "id": 29343160,
    "properties": {
        "woe_id": 29343160,
        "place_id": "Y3afc42bCJ_wMEcrYA",
        "place_type": "locality",
        "place_type_id": 7,
        "label": "Bell'italia, Emilia Romagna, Italy"
    },
    "geometry": {
        "type": "MultiPolygon",
        "created": 1292540108,
        "alpha": 0.00015,
        "points": 12,
        "edges": 7,
        "is_donuthole": 0,
        "link": {
            "href": "http:\/\/farm6.static.flickr.com\/5162\/shapefiles\/29343160_20101216_dd89ec6a3f.tar.gz"
        },
        "bbox": [
            10.867195129395,
            44.527965545654,
            10.879467964172,
            44.537975311279
        ],
        "coordinates": [
            [
                [
                    [
                        10.872044,
                        44.536713
                    ],
                    [
                        10.879468,
                        44.536224
                    ],
                    [
                        10.877408,
                        44.530598
                    ],
                    [
                        10.872259,
                        44.527966
                    ],
                    [
                        10.867195,
                        44.52882
                    ],
                    [
                        10.867924,
                        44.537975
                    ],
                    [
                        10.872044,
                        44.536713
                    ]
                ]
            ]
        ]
    }
}