{
    "type": "Feature",
    "id": 20222699,
    "properties": {
        "woe_id": 20222699,
        "place_id": "xjDCbyabAZ482s4MRw",
        "place_type": "locality",
        "place_type_id": 7,
        "label": "El Pintado, Andalusia, Spain"
    },
    "geometry": {
        "type": "MultiPolygon",
        "created": 1292534798,
        "alpha": 0.00015,
        "points": 17,
        "edges": 5,
        "is_donuthole": 0,
        "link": {
            "href": "http:\/\/farm6.static.flickr.com\/5201\/shapefiles\/20222699_20101216_07b24cc282.tar.gz"
        },
        "bbox": [
            -5.957142829895,
            37.978168487549,
            -5.9477229118347,
            37.988418579102
        ],
        "coordinates": [
            [
                [
                    [
                        -5.957143,
                        37.985947
                    ],
                    [
                        -5.956306,
                        37.988419
                    ],
                    [
                        -5.947723,
                        37.981819
                    ],
                    [
                        -5.953731,
                        37.978168
                    ],
                    [
                        -5.957143,
                        37.985947
                    ]
                ]
            ]
        ]
    }
}