{
    "type": "Feature",
    "id": 2461299,
    "properties": {
        "woe_id": 2461299,
        "place_id": "oaUDU7ubBZqw9qDa",
        "place_type": "neighbourhood",
        "place_type_id": 22,
        "label": "North Lovell, Stoneham, ME, US, United States"
    },
    "geometry": {
        "type": "MultiPolygon",
        "created": 1292486349,
        "alpha": 4.0690104166667e-5,
        "points": 11,
        "edges": 9,
        "is_donuthole": 0,
        "link": {
            "href": "http:\/\/farm6.static.flickr.com\/5207\/shapefiles\/2461299_20101216_d93ec0ae90.tar.gz"
        },
        "bbox": [
            -70.864822387695,
            44.263687133789,
            -70.856727600098,
            44.26895904541
        ],
        "coordinates": [
            [
                [
                    [
                        -70.856728,
                        44.268021
                    ],
                    [
                        -70.863235,
                        44.264034
                    ],
                    [
                        -70.863876,
                        44.263779
                    ],
                    [
                        -70.86422,
                        44.263687
                    ],
                    [
                        -70.864822,
                        44.263748
                    ],
                    [
                        -70.863235,
                        44.264034
                    ],
                    [
                        -70.858124,
                        44.268589
                    ],
                    [
                        -70.856834,
                        44.268959
                    ],
                    [
                        -70.856728,
                        44.268021
                    ]
                ]
            ]
        ]
    }
}